{
  "type": "minecraft:chest",
  "pools": [
    {
      "bonus_rolls": 0.0,
      "entries": [
        {
          "type": "minecraft:item",
          "functions": [
            {
              "function": "minecraft:limit_count",
              "limit": 1.0
            }
          ],
          "name": "minecraft:iron_shovel"
        },
        {
          "type": "minecraft:item",
          "functions": [
            {
              "function": "minecraft:limit_count",
              "limit": 1.0
            }
          ],
          "name": "minecraft:brush"
        },
        {
          "type": "minecraft:item",
          "functions": [
            {
              "function": "minecraft:limit_count",
              "limit": 1.0
            }
          ],
          "name": "minecraft:spyglass"
        },
        {
          "type": "minecraft:item",
          "functions": [
            {
              "function": "minecraft:limit_count",
              "limit": 1.0
            }
          ],
          "name": "minecraft:compass"
        },
        {
          "type": "minecraft:item",
          "name": "minecraft:flint",
          "weight": 4
        },
        {
          "type": "minecraft:item",
          "name": "minecraft:stick",
          "weight": 2
        },
        {
          "type": "minecraft:item",
          "name": "minecraft:gold_ingot"
        },
        {
          "type": "minecraft:item",
          "name": "minecraft:emerald",
          "weight": 3
        }
      ],
      "rolls": {
        "type": "minecraft:uniform",
        "max": 14.0,
        "min": 9.0
      }
    }
  ]
}